[
  {
    "timestamp": "2025-10-11T05:33:39.186105",
    "location": "NYC",
    "latitude": 40.7128,
    "longitude": -74.006,
    "temperature_celsius": 19.87,
    "temperature_fahrenheit": 67.77,
    "humidity_percent": 45.4,
    "pressure_hpa": 1020.8,
    "wind_speed_kmh": 9.9,
    "weather_condition": "cloudy",
    "visibility_km": 8.8,
    "uv_index": 0,
    "hour": 5,
    "day_of_week": 5,
    "is_weekend": true
  },
  {
    "timestamp": "2025-10-11T04:33:39.186105",
    "location": "NYC",
    "latitude": 40.7128,
    "longitude": -74.006,
    "temperature_celsius": 10.85,
    "temperature_fahrenheit": 51.53,
    "humidity_percent": 73.8,
    "pressure_hpa": 1020.7,
    "wind_speed_kmh": 7.8,
    "weather_condition": "cloudy",
    "visibility_km": 3.5,
    "uv_index": 0,
    "hour": 4,
    "day_of_week": 5,
    "is_weekend": true
  },
  {
    "timestamp": "2025-10-11T03:33:39.186105",
    "location": "NYC",
    "latitude": 40.7128,
    "longitude": -74.006,
    "temperature_celsius": 30.87,
    "temperature_fahrenheit": 87.56,
    "humidity_percent": 90.0,
    "pressure_hpa": 1008.3,
    "wind_speed_kmh": 13.6,
    "weather_condition": "rain",
    "visibility_km": 13.7,
    "uv_index": 0,
    "hour": 3,
    "day_of_week": 5,
    "is_weekend": true
  },
  {
    "timestamp": "2025-10-11T02:33:39.186105",
    "location": "NYC",
    "latitude": 40.7128,
    "longitude": -74.006,
    "temperature_celsius": 21.95,
    "temperature_fahrenheit": 71.5,
    "humidity_percent": 69.2,
    "pressure_hpa": 1017.5,
    "wind_speed_kmh": 12.0,
    "weather_condition": "cloudy",
    "visibility_km": 9.9,
    "uv_index": 0,
    "hour": 2,
    "day_of_week": 5,
    "is_weekend": true
  },
  {
    "timestamp": "2025-10-11T01:33:39.186105",
    "location": "NYC",
    "latitude": 40.7128,
    "longitude": -74.006,
    "temperature_celsius": 17.71,
    "temperature_fahrenheit": 63.88,
    "humidity_percent": 87.4,
    "pressure_hpa": 1029.4,
    "wind_speed_kmh": 8.8,
    "weather_condition": "fog",
    "visibility_km": 3.2,
    "uv_index": 0,
    "hour": 1,
    "day_of_week": 5,
    "is_weekend": true
  },
  {
    "timestamp": "2025-10-11T00:33:39.186105",
    "location": "NYC",
    "latitude": 40.7128,
    "longitude": -74.006,
    "temperature_celsius": 18.68,
    "temperature_fahrenheit": 65.62,
    "humidity_percent": 82.5,
    "pressure_hpa": 1028.9,
    "wind_speed_kmh": 3.8,
    "weather_condition": "clear",
    "visibility_km": 6.0,
    "uv_index": 0,
    "hour": 0,
    "day_of_week": 5,
    "is_weekend": true
  },
  {
    "timestamp": "2025-10-10T23:33:39.186105",
    "location": "NYC",
    "latitude": 40.7128,
    "longitude": -74.006,
    "temperature_celsius": 30.53,
    "temperature_fahrenheit": 86.95,
    "humidity_percent": 80.1,
    "pressure_hpa": 1029.8,
    "wind_speed_kmh": 11.5,
    "weather_condition": "clear",
    "visibility_km": 12.9,
    "uv_index": 0,
    "hour": 23,
    "day_of_week": 4,
    "is_weekend": false
  },
  {
    "timestamp": "2025-10-10T22:33:39.186105",
    "location": "NYC",
    "latitude": 40.7128,
    "longitude": -74.006,
    "temperature_celsius": 28.62,
    "temperature_fahrenheit": 83.51,
    "humidity_percent": 57.8,
    "pressure_hpa": 1025.7,
    "wind_speed_kmh": 4.3,
    "weather_condition": "clear",
    "visibility_km": 13.9,
    "uv_index": 0,
    "hour": 22,
    "day_of_week": 4,
    "is_weekend": false
  },
  {
    "timestamp": "2025-10-10T21:33:39.186105",
    "location": "NYC",
    "latitude": 40.7128,
    "longitude": -74.006,
    "temperature_celsius": 21.49,
    "temperature_fahrenheit": 70.68,
    "humidity_percent": 70,
    "pressure_hpa": 1010.5,
    "wind_speed_kmh": 1.9,
    "weather_condition": "rain",
    "visibility_km": 11.8,
    "uv_index": 0,
    "hour": 21,
    "day_of_week": 4,
    "is_weekend": false
  },
  {
    "timestamp": "2025-10-10T20:33:39.186105",
    "location": "NYC",
    "latitude": 40.7128,
    "longitude": -74.006,
    "temperature_celsius": 18.28,
    "temperature_fahrenheit": 64.9,
    "humidity_percent": 73.5,
    "pressure_hpa": 1016.4,
    "wind_speed_kmh": 12.1,
    "weather_condition": "clear",
    "visibility_km": 13.3,
    "uv_index": 0,
    "hour": 20,
    "day_of_week": 4,
    "is_weekend": false
  },
  {
    "timestamp": "2025-10-10T19:33:39.186105",
    "location": "NYC",
    "latitude": 40.7128,
    "longitude": -74.006,
    "temperature_celsius": 8.68,
    "temperature_fahrenheit": 47.63,
    "humidity_percent": 86.2,
    "pressure_hpa": 1009.3,
    "wind_speed_kmh": 2.9,
    "weather_condition": "clear",
    "visibility_km": 9.5,
    "uv_index": 0,
    "hour": 19,
    "day_of_week": 4,
    "is_weekend": false
  },
  {
    "timestamp": "2025-10-10T18:33:39.186105",
    "location": "NYC",
    "latitude": 40.7128,
    "longitude": -74.006,
    "temperature_celsius": 26.86,
    "temperature_fahrenheit": 80.35,
    "humidity_percent": 88.1,
    "pressure_hpa": 1022.1,
    "wind_speed_kmh": 1.0,
    "weather_condition": "clear",
    "visibility_km": 10.6,
    "uv_index": 3.8,
    "hour": 18,
    "day_of_week": 4,
    "is_weekend": false
  },
  {
    "timestamp": "2025-10-10T17:33:39.186105",
    "location": "NYC",
    "latitude": 40.7128,
    "longitude": -74.006,
    "temperature_celsius": 13.29,
    "temperature_fahrenheit": 55.93,
    "humidity_percent": 55.5,
    "pressure_hpa": 1018.2,
    "wind_speed_kmh": 6.6,
    "weather_condition": "cloudy",
    "visibility_km": 12.2,
    "uv_index": 6.2,
    "hour": 17,
    "day_of_week": 4,
    "is_weekend": false
  },
  {
    "timestamp": "2025-10-10T16:33:39.186105",
    "location": "NYC",
    "latitude": 40.7128,
    "longitude": -74.006,
    "temperature_celsius": 28.92,
    "temperature_fahrenheit": 84.05,
    "humidity_percent": 83.2,
    "pressure_hpa": 1002.9,
    "wind_speed_kmh": 5.4,
    "weather_condition": "cloudy",
    "visibility_km": 7.1,
    "uv_index": 1.9,
    "hour": 16,
    "day_of_week": 4,
    "is_weekend": false
  },
  {
    "timestamp": "2025-10-10T15:33:39.186105",
    "location": "NYC",
    "latitude": 40.7128,
    "longitude": -74.006,
    "temperature_celsius": 34.23,
    "temperature_fahrenheit": 93.62,
    "humidity_percent": 87.5,
    "pressure_hpa": 1014.0,
    "wind_speed_kmh": 9.1,
    "weather_condition": "clear",
    "visibility_km": 5.4,
    "uv_index": 7.5,
    "hour": 15,
    "day_of_week": 4,
    "is_weekend": false
  },
  {
    "timestamp": "2025-10-10T14:33:39.186105",
    "location": "NYC",
    "latitude": 40.7128,
    "longitude": -74.006,
    "temperature_celsius": 29.71,
    "temperature_fahrenheit": 85.48,
    "humidity_percent": 40.0,
    "pressure_hpa": 1019.5,
    "wind_speed_kmh": 14.9,
    "weather_condition": "cloudy",
    "visibility_km": 8.2,
    "uv_index": 7.8,
    "hour": 14,
    "day_of_week": 4,
    "is_weekend": false
  },
  {
    "timestamp": "2025-10-10T13:33:39.186105",
    "location": "NYC",
    "latitude": 40.7128,
    "longitude": -74.006,
    "temperature_celsius": 25.98,
    "temperature_fahrenheit": 78.77,
    "humidity_percent": 70,
    "pressure_hpa": 1009.7,
    "wind_speed_kmh": 14.6,
    "weather_condition": "rain",
    "visibility_km": 4.5,
    "uv_index": 5.2,
    "hour": 13,
    "day_of_week": 4,
    "is_weekend": false
  },
  {
    "timestamp": "2025-10-10T12:33:39.186105",
    "location": "NYC",
    "latitude": 40.7128,
    "longitude": -74.006,
    "temperature_celsius": 27.32,
    "temperature_fahrenheit": 81.18,
    "humidity_percent": 70,
    "pressure_hpa": 1013.9,
    "wind_speed_kmh": 4.8,
    "weather_condition": "rain",
    "visibility_km": 5.2,
    "uv_index": 2.1,
    "hour": 12,
    "day_of_week": 4,
    "is_weekend": false
  },
  {
    "timestamp": "2025-10-10T11:33:39.186105",
    "location": "NYC",
    "latitude": 40.7128,
    "longitude": -74.006,
    "temperature_celsius": 30.48,
    "temperature_fahrenheit": 86.86,
    "humidity_percent": 34.4,
    "pressure_hpa": 1010.9,
    "wind_speed_kmh": 5.0,
    "weather_condition": "clear",
    "visibility_km": 2.9,
    "uv_index": 6.0,
    "hour": 11,
    "day_of_week": 4,
    "is_weekend": false
  },
  {
    "timestamp": "2025-10-10T10:33:39.186105",
    "location": "NYC",
    "latitude": 40.7128,
    "longitude": -74.006,
    "temperature_celsius": 29.08,
    "temperature_fahrenheit": 84.35,
    "humidity_percent": 30.8,
    "pressure_hpa": 1016.1,
    "wind_speed_kmh": 0.6,
    "weather_condition": "cloudy",
    "visibility_km": 3.9,
    "uv_index": 3.4,
    "hour": 10,
    "day_of_week": 4,
    "is_weekend": false
  },
  {
    "timestamp": "2025-10-10T09:33:39.186105",
    "location": "NYC",
    "latitude": 40.7128,
    "longitude": -74.006,
    "temperature_celsius": 12.66,
    "temperature_fahrenheit": 54.79,
    "humidity_percent": 57.6,
    "pressure_hpa": 1024.0,
    "wind_speed_kmh": 4.3,
    "weather_condition": "clear",
    "visibility_km": 10.5,
    "uv_index": 2.8,
    "hour": 9,
    "day_of_week": 4,
    "is_weekend": false
  },
  {
    "timestamp": "2025-10-10T08:33:39.186105",
    "location": "NYC",
    "latitude": 40.7128,
    "longitude": -74.006,
    "temperature_celsius": 15.19,
    "temperature_fahrenheit": 59.34,
    "humidity_percent": 49.3,
    "pressure_hpa": 1027.0,
    "wind_speed_kmh": 8.9,
    "weather_condition": "clear",
    "visibility_km": 2.2,
    "uv_index": 0.6,
    "hour": 8,
    "day_of_week": 4,
    "is_weekend": false
  },
  {
    "timestamp": "2025-10-10T07:33:39.186105",
    "location": "NYC",
    "latitude": 40.7128,
    "longitude": -74.006,
    "temperature_celsius": 17.41,
    "temperature_fahrenheit": 63.34,
    "humidity_percent": 55.7,
    "pressure_hpa": 1000.4,
    "wind_speed_kmh": 8.8,
    "weather_condition": "clear",
    "visibility_km": 4.6,
    "uv_index": 3.3,
    "hour": 7,
    "day_of_week": 4,
    "is_weekend": false
  },
  {
    "timestamp": "2025-10-10T06:33:39.186105",
    "location": "NYC",
    "latitude": 40.7128,
    "longitude": -74.006,
    "temperature_celsius": 25.22,
    "temperature_fahrenheit": 77.4,
    "humidity_percent": 47.7,
    "pressure_hpa": 1022.1,
    "wind_speed_kmh": 2.3,
    "weather_condition": "cloudy",
    "visibility_km": 5.3,
    "uv_index": 1.9,
    "hour": 6,
    "day_of_week": 4,
    "is_weekend": false
  }
]